<?xml version="1.0" encoding="UTF-8"?>
<testcase id="egfoBorderStyle4" parentName="block" xmlns:fo="http://www.w3.org/1999/XSL/Format">
      <parentText>The border style properties for this image are set to "groove".</parentText>
      <fo foName="external-graphic">
       <foProperty name="src" value="nist.jpg"/>
       <foProperty name="border-before-style" value="groove"/>
       <foProperty name="border-after-style" value="groove"/>
       <foProperty name="border-start-style" value="groove"/>
       <foProperty name="border-end-style" value="groove"/>
      </fo>
  </testcase>
